msm_design/__init__.py
msm_design/msm_model.py
msm_design/msm_optimization.py
msm_design/data/Msm_Design_Runner.py
msm_design/data/smallalignment.txt
msm_design/data/ubiquitin_State0_energies_amber_4positionmutations_top4AA.txt
msm_design/data/ubiquitin_State0_energies_rosetta_4positionmutations_top4AA.txt
msm_design/data/model_files/w_nopairnoweight_State0.txt
msm_design/data/model_files/w_nopairnoweight_State1.txt
msm_design/data/model_files/w_nopairnoweight_State2.txt
msm_design/data/model_files/w_nopairnoweight_State3.txt
msm_design/data/model_files/w_nopairnoweight_State4.txt
msm_design/data/model_files/w_nopairnoweight_State5.txt
msm_design/data/model_files/w_nopairnoweight_State6.txt
msm_design/data/model_files/w_nopairnoweight_State7.txt
msm_design/data/model_files/w_nopairnoweight_State8.txt
msm_design/data/model_files/w_nopairnoweight_State9.txt
msm_design/data/pdb_files/State0.pdb
msm_design/data/pdb_files/State1.pdb
msm_design/data/pdb_files/State2.pdb
msm_design/data/pdb_files/State3.pdb
msm_design/data/pdb_files/State4.pdb
msm_design/data/pdb_files/State5.pdb
msm_design/data/pdb_files/State6.pdb
msm_design/data/pdb_files/State7.pdb
msm_design/data/pdb_files/State8.pdb
msm_design/data/pdb_files/State9.pdb
msm_design-0.12.dist-info/DESCRIPTION.rst
msm_design-0.12.dist-info/METADATA
msm_design-0.12.dist-info/RECORD
msm_design-0.12.dist-info/WHEEL
msm_design-0.12.dist-info/metadata.json
msm_design-0.12.dist-info/top_level.txt
