Metadata-Version: 1.0
Name: msm-design
Version: 0.12
Summary: Markov State Modeling Protein Design Package utilizing Machine Learning and Brute Force Optimization of a specified conformational state of a protein
Home-page: https://github.com/thinkle12/msm_design/
Author: Trent Hinkle
Author-email: trenth12@gmail.com
License: UNKNOWN
Platform: UNKNOWN
